PyXMake/API/__init__.py
pyx_webservice-1.28.0.dist-info/METADATA
pyx_webservice-1.28.0.dist-info/WHEEL
pyx_webservice-1.28.0.dist-info/RECORD
